touchpy-0.10.0.data/purelib/touchpy/TouchEngine.dll
touchpy-0.10.0.data/purelib/touchpy/__init__.py
touchpy-0.10.0.data/purelib/touchpy/cudart64_110.dll
touchpy-0.10.0.data/purelib/touchpy/fmt.dll
touchpy-0.10.0.data/purelib/touchpy/spdlog.dll
touchpy-0.10.0.data/purelib/touchpy/touchpy.cp310-win_amd64.pyd
touchpy-0.10.0.data/purelib/touchpy/touchpy.cp311-win_amd64.pyd
touchpy-0.10.0.data/purelib/touchpy/touchpy.cp39-win_amd64.pyd
touchpy-0.10.0.dist-info/LICENSE.md
touchpy-0.10.0.dist-info/METADATA
touchpy-0.10.0.dist-info/WHEEL
touchpy-0.10.0.dist-info/top_level.txt
touchpy-0.10.0.dist-info/RECORD
