Metadata-Version: 2.1
Name: touchpy
Version: 0.10.0
Summary: TouchPy is a high-performance toolset to work with TouchDesigner components in Python
Author-email: Keith Lostracco <keith@intentdev.io>, Idzard Kwadijk <idzard@intentdev.io>
License: # PolyForm Noncommercial License 1.0.0
Project-URL: Documentation, https://intentdev.github.io/touchpy/
Project-URL: GitHub, https://github.com/IntentDev/touchpy
Classifier: Programming Language :: Python :: 3.9
Classifier: Programming Language :: Python :: 3.10
Classifier: Programming Language :: Python :: 3.11
Classifier: Programming Language :: Python :: 3.12
Classifier: Operating System :: Microsoft :: Windows
Requires-Python: <3.13,>=3.9
License-File: LICENSE.md
